setup.py
jher.egg-info/PKG-INFO
jher.egg-info/SOURCES.txt
jher.egg-info/dependency_links.txt
jher.egg-info/top_level.txt
mark/__init__.py
mark/label_main.py