Metadata-Version: 2.1
Name: jher
Version: 0.0.1
Summary: use for test
Home-page: UNKNOWN
Author: jh
Author-email: jhdyxa@163.com
License: UNKNOWN
Platform: UNKNOWN
Requires: ahocorasick
